{
  "gitSyncId": "66d58fbcb85ef160f28f7abd_dbcebb7c-a43b-4ec0-a230-4f932336be22",
  "id": "MainPage_utilsClass.calcolaPunteggio",
  "pluginId": "js-plugin",
  "pluginType": "JS",
  "unpublishedAction": {
    "actionConfiguration": {
      "encodeParamsToggle": true,
      "jsArguments": [
        {
          "name": "currentRow"
        }
      ],
      "paginationType": "NONE",
      "timeoutInMillisecond": 10000
    },
    "clientSideExecution": true,
    "collectionId": "MainPage_utilsClass",
    "confirmBeforeExecute": false,
    "datasource": {
      "isAutoGenerated": false,
      "name": "UNUSED_DATASOURCE",
      "pluginId": "js-plugin"
    },
    "dynamicBindingPathList": [
      {
        "key": "body"
      }
    ],
    "executeOnLoad": false,
    "fullyQualifiedName": "utilsClass.calcolaPunteggio",
    "name": "calcolaPunteggio",
    "pageId": "MainPage",
    "userSetOnLoad": false
  }
}